moviesampler/__init__.py
moviesampler/framegrabber.py
moviesampler/imagecomposer.py
moviesampler/main.py
moviesampler/fonts/3270-Regular.otf
moviesampler/fonts/3270Condensed-Regular.otf
moviesampler-1.2.dist-info/LICENSE
moviesampler-1.2.dist-info/METADATA
moviesampler-1.2.dist-info/WHEEL
moviesampler-1.2.dist-info/entry_points.txt
moviesampler-1.2.dist-info/top_level.txt
moviesampler-1.2.dist-info/RECORD
