Metadata-Version: 2.1
Name: moviesampler
Version: 1.2
Summary: Video file thumbnailer
Author-email: Javier Llopis <javier@llopis.me>
Project-URL: Repository, https://github.com/destrangis/moviesampler
Classifier: Development Status :: 4 - Beta
Classifier: Environment :: Console
Classifier: Intended Audience :: End Users/Desktop
Classifier: License :: OSI Approved :: MIT License
Classifier: Operating System :: OS Independent
Classifier: Programming Language :: Python :: 3.10
Classifier: Programming Language :: Python :: 3.11
Classifier: Programming Language :: Python :: 3.12
Classifier: Programming Language :: Python :: 3.13
Classifier: Topic :: Artistic Software
Classifier: Topic :: Multimedia :: Graphics
Classifier: Topic :: Multimedia :: Graphics :: Presentation
Classifier: Topic :: Multimedia :: Video
Classifier: Topic :: Utilities
Requires-Python: >=3.10
License-File: LICENSE
Requires-Dist: av
Requires-Dist: pillow
